{"GeneratedCodeFiles":[],"GeneratedXamlFiles":["c:\\Users\\45425\\Desktop\\FED\\FED\\Lektion1\\obj\\Debug\\net9.0-windows10.0.19041.0\\win10-x64\\Platforms\\Windows\\App.xaml"],"GeneratedXbfFiles":["c:\\Users\\45425\\Desktop\\FED\\FED\\Lektion1\\obj\\Debug\\net9.0-windows10.0.19041.0\\win10-x64\\Platforms\\Windows\\App.xbf"],"GeneratedXamlPagesFiles":[],"MSBuildLogEntries":[{"SubCategory":null,"ErrorCode":null,"HelpKeyword":null,"File":null,"LineNumber":0,"ColumnNumber":0,"EndLineNumber":0,"EndColumnNumber":0,"Message":"Xaml Compiler Marker: 18.44.52: 284 perfXC_StartPass2, Lektion1"},{"SubCategory":null,"ErrorCode":null,"HelpKeyword":null,"File":null,"LineNumber":0,"ColumnNumber":0,"EndLineNumber":0,"EndColumnNumber":0,"Message":"Xaml Compiler Marker: 18.44.52: 357 perfXC_FingerprintCheck, Using managed HashForWinMD"},{"SubCategory":null,"ErrorCode":null,"HelpKeyword":null,"File":null,"LineNumber":0,"ColumnNumber":0,"EndLineNumber":0,"EndColumnNumber":0,"Message":"Xaml Compiler Marker: 18.44.52: 915 perfXC_FingerprintCheck, Using managed HashForWinMD"},{"SubCategory":null,"ErrorCode":null,"HelpKeyword":null,"File":null,"LineNumber":0,"ColumnNumber":0,"EndLineNumber":0,"EndColumnNumber":0,"Message":"Xaml Compiler Marker: 18.44.52: 962 perfXC_RestoredGeneratedPass2CodeFileBackup"},{"SubCategory":null,"ErrorCode":null,"HelpKeyword":null,"File":null,"LineNumber":0,"ColumnNumber":0,"EndLineNumber":0,"EndColumnNumber":0,"Message":"Xaml Compiler Marker: 18.44.52: 984 perfXC_RestoredTypeInfoBackup"}]}